{"name":"build-javascript","namedChunkGroups":{"polyfill":{"name":"polyfill","assets":[{"name":"webpack-runtime-e85e5e524b5530c44101.js","size":4987},{"name":"polyfill-28dbfa58150ea9910781.js","size":85836}],"filteredAssets":0,"assetsSize":90823,"filteredAuxiliaryAssets":2,"auxiliaryAssetsSize":227831},"app":{"name":"app","assets":[{"name":"webpack-runtime-e85e5e524b5530c44101.js","size":4987},{"name":"styles.f62d1f1136fce0a88e2c.css","size":35075},{"name":"framework-deb5402af5b406c6372a.js","size":129749},{"name":"cb1608f2-05e41aa4c100271cad68.js","size":1536},{"name":"f357f4e3-0693f0028ff6c0c7f826.js","size":1155},{"name":"app-0fe6b916c4adcb48cb18.js","size":148566}],"filteredAssets":0,"assetsSize":321068,"filteredAuxiliaryAssets":11,"auxiliaryAssetsSize":15011725},"component---src-pages-404-tsx":{"name":"component---src-pages-404-tsx","assets":[{"name":"component---src-pages-404-tsx-9aa66438d944abc5ead2.js","size":803}],"filteredAssets":0,"assetsSize":803,"filteredAuxiliaryAssets":1,"auxiliaryAssetsSize":2038},"component---src-pages-index-tsx":{"name":"component---src-pages-index-tsx","assets":[{"name":"styles.f62d1f1136fce0a88e2c.css","size":35075},{"name":"component---src-pages-index-tsx-c9a1b8f81a2dd2f15514.js","size":22719}],"filteredAssets":0,"assetsSize":57794,"filteredAuxiliaryAssets":1,"auxiliaryAssetsSize":89917},"component---src-pages-privacy-tsx":{"name":"component---src-pages-privacy-tsx","assets":[{"name":"styles.f62d1f1136fce0a88e2c.css","size":35075},{"name":"component---src-pages-privacy-tsx-82642b5e5894bc00e8cb.js","size":4436}],"filteredAssets":0,"assetsSize":39511,"filteredAuxiliaryAssets":1,"auxiliaryAssetsSize":12350}},"assetsByChunkName":{"polyfill":["webpack-runtime-e85e5e524b5530c44101.js","polyfill-28dbfa58150ea9910781.js"],"app":["webpack-runtime-e85e5e524b5530c44101.js","styles.f62d1f1136fce0a88e2c.css","framework-deb5402af5b406c6372a.js","cb1608f2-05e41aa4c100271cad68.js","f357f4e3-0693f0028ff6c0c7f826.js","app-0fe6b916c4adcb48cb18.js"],"component---src-pages-404-tsx":["component---src-pages-404-tsx-9aa66438d944abc5ead2.js"],"component---src-pages-index-tsx":["styles.f62d1f1136fce0a88e2c.css","component---src-pages-index-tsx-c9a1b8f81a2dd2f15514.js"],"component---src-pages-privacy-tsx":["styles.f62d1f1136fce0a88e2c.css","component---src-pages-privacy-tsx-82642b5e5894bc00e8cb.js"]},"childAssetsByChunkName":{}}